{
  "id": "posadzka-zywiczna-garaz-domowy-krakow",
  "slug": "posadzka-zywiczna-garaz-domowy-krakow",
  "title": "Posadzka żywiczna garaż domowy Kraków – idealna dla Twojego domu",
  "excerpt": "Posadzka żywiczna do garażu w domu jednorodzinnym w Krakowie. Systemy, ceny, kolory i realizacja dla właścicieli domów.",
  "content": "\n<p>Budujesz lub modernizujesz dom jednorodzinny w <strong>Krakowie</strong>? <strong>Posadzka żywiczna w garażu</strong> to inwestycja, która podnosi wartość Twojej nieruchomości i zapewnia komfort użytkowania na lata.</p>\n\n<h2>Dlaczego posadzka żywiczna w garażu domowym?</h2>\n<p>Garaż w domu jednorodzinnym w Krakowie to nie tylko miejsce parkowania. To także:</p>\n<ul>\n  <li><strong>Warsztat domowy</strong> – miejsce na narzędzia i majsterkowanie</li>\n  <li><strong>Strefa wejściowa</strong> – pierwsze pomieszczenie przy wejściu do domu</li>\n  <li><strong>Magazyn</strong> – przechowywanie sprzętu, opon, rowerów</li>\n  <li><strong>Wizytówka domu</strong> – estetyka ma znaczenie</li>\n</ul>\n<p>Posadzka żywiczna spełnia wszystkie wymogi funkcjonalne i estetyczne.</p>\n\n<h2>Zalety dla domu jednorodzinnego</h2>\n<ul>\n  <li><strong>Wartość nieruchomości</strong> – profesjonalny garaż to +3-5% do wartości domu</li>\n  <li><strong>Łatwość czyszczenia</strong> – gładka powierzchnia, brak kurzu w domu</li>\n  <li><strong>Estetyka</strong> – nowoczesny, elegancki wygląd</li>\n  <li><strong>Higieniczny</strong> – bezpyłowa powierzchnia lepsza dla zdrowia</li>\n  <li><strong>Trwałość</strong> – 25-30 lat w garażu prywatnym</li>\n  <li><strong>Bezpieczeństwo</strong> – struktura antypoślizgowa opcjonalnie</li>\n  <li><strong>Personalizacja</strong> – dowolne kolory i efekty</li>\n</ul>\n\n<h2>Garaże domowe w różnych dzielnicach Krakowa</h2>\n\n<h3>Dzielnice w zachodnim Krakowie</h3>\n<p><strong>Bronowice, Wola Justowska, Zwierzyniec:</strong></p>\n<ul>\n  <li>Domy jednorodzinne duże (150-300 m²)</li>\n  <li>Garaże 2-3 stanowiskowe (40-60 m²)</li>\n  <li>Wysoki standard wykończenia</li>\n  <li><strong>Zalecenie</strong>: posadzka premium z efektem dekoracyjnym</li>\n  <li><strong>Cena</strong>: 250-380 zł/m²</li>\n</ul>\n\n<h3>Dzielnice w północnym Krakowie</h3>\n<p><strong>Prądnik, Krowodrza, Azory:</strong></p>\n<ul>\n  <li>Domy jednorodzinne średnie (120-180 m²)</li>\n  <li><strong>Garaże 1-2 stanowiskowe (20-40 m²)</strong></li>\n  <li>Standard średni do wysokiego</li>\n  <li><strong>Zalecenie</strong>: posadzka epoksydowa 2-3 mm</li>\n  <li><strong>Cena</strong>: 200-280 zł/m²</li>\n</ul>\n\n<h3>Dzielnice w południowym Krakowie</h3>\n<p><strong>Podgórze, Swoszowice, Wola Duchacka:</strong></p>\n<ul>\n  <li>Domy różnej wielkości (80-200 m²)</li>\n  <li>Garaże 1-2 stanowiskowe (18-36 m²)</li>\n  <li>Standard zróżnicowany</li>\n  <li><strong>Zalecenie</strong>: posadzka epoksydowa standardowa</li>\n  <li><strong>Cena</strong>: 180-250 zł/m²</li>\n</ul>\n\n<h3>Peryferie Krakowa</h3>\n<p><strong>Łagiewniki, Bieżanów, Prokocim:</strong></p>\n<ul>\n  <li>Nowe osiedła domów (100-150 m²)</li>\n  <li>Garaże wbudowane lub przybudowane</li>\n  <li>Standard średni</li>\n  <li><strong>Zalecenie</strong>: epoksyd 2mm, dobra relacja ceny do jakości</li>\n  <li><strong>Cena</strong>: 160-220 zł/m²</li>\n</ul>\n\n<h2>Jaki system wybrać dla garażu domowego?</h2>\n\n<h3>Garaż z bezpośrednim wejściem do domu</h3>\n<ul>\n  <li><strong>Priorytet</strong>: estetyka i czystość</li>\n  <li><strong>System</strong>: epoksyd 2-3 mm z topcoatem premium</li>\n  <li><strong>Kolor</strong>: jasny (RAL 7035, 9002) – rozjaśnia wnętrze</li>\n  <li><strong>Opcja</strong>: posypka drobna R10 dla bezpieczeństwa przy wejściu</li>\n  <li><strong>Cena</strong>: 220-300 zł/m²</li>\n</ul>\n\n<h3>Garaż z oknami lub świetlikami</h3>\n<ul>\n  <li><strong>Uwaga</strong>: dostęp światła słonecznego</li>\n  <li><strong>System</strong>: poliuretan 2-3 mm (odporność UV) lub epoksyd + topcoat UV</li>\n  <li><strong>Kolor</strong>: dowolny (nie żółknie)</li>\n  <li><strong>Cena</strong>: 300-420 zł/m² (poliuretan) lub 200-280 zł/m² (epoksyd+UV)</li>\n</ul>\n\n<h3>Garaż wolnostojący</h3>\n<ul>\n  <li><strong>Uwaga</strong>: większe wahania temperatury</li>\n  <li><strong>System</strong>: epoksyd 2mm lub poliuretan (bardziej elastyczny)</li>\n  <li><strong>Cena</strong>: 180-250 zł/m² (epoksyd) lub 300-380 zł/m² (poliuretan)</li>\n</ul>\n\n<h3>Garaż z warsztatem</h3>\n<ul>\n  <li><strong>Priorytet</strong>: wytrzymałość na upadki narzędzi</li>\n  <li><strong>System</strong>: epoksyd 3-4 mm grubowarstwowy</li>\n  <li><strong>Opcja</strong>: posypka R11 w strefie roboczej</li>\n  <li><strong>Cena</strong>: 280-380 zł/m²</li>\n</ul>\n\n<h2>Kolory i efekty dla garaży domowych</h2>\n\n<h3>Klasyczne monochromatyczne</h3>\n<ul>\n  <li><strong>RAL 7035</strong> (jasnoszary) – najbardziej popularny, uniwersalny</li>\n  <li><strong>RAL 7037</strong> (szary pyłowy) – nowoczesny, elegancki</li>\n  <li><strong>RAL 9002</strong> (białoszary) – rozjaśnia wnętrze</li>\n  <li><strong>RAL 7040</strong> (szary okienny) – ciemniejszy, ukrywa brudy</li>\n  <li><strong>Dopłata</strong>: 0 zł (kolory standardowe)</li>\n</ul>\n\n<h3>Dwukolorowe</h3>\n<ul>\n  <li><strong>Koncepcja</strong>: miejsca postojowe w jednym kolorze, droga w drugim</li>\n  <li><strong>Przykład</strong>: RAL 7035 + RAL 7040 (jasny + ciemny)</li>\n  <li><strong>Efekt</strong>: wydzielenie stref, estetyka</li>\n  <li><strong>Dopłata</strong>: +30-50 zł/m² (drugi kolor)</li>\n</ul>\n\n<h3>Z flock (floki kolorowe)</h3>\n<ul>\n  <li><strong>Koncepcja</strong>: drobne płatki kolorowe w żywicy</li>\n  <li><strong>Efekt</strong>: dynamiczny, dekoracyjny, ukrywa drobne zabrudzenia</li>\n  <li><strong>Kolory</strong>: szary/biały/czarny lub kolorowy mix</li>\n  <li><strong>Dopłata</strong>: +50-80 zł/m²</li>\n</ul>\n\n<h3>Efekt metallic</h3>\n<ul>\n  <li><strong>Koncepcja</strong>: pigmenty metaliczne w żywicy</li>\n  <li><strong>Efekt</strong>: błyszcząca, luksusowa powierzchnia</li>\n  <li><strong>Kolory</strong>: srebrny, złoty, miedziany</li>\n  <li><strong>Dopłata</strong>: +80-150 zł/m²</li>\n</ul>\n\n<h3>Imitacja betonu architektonicznego</h3>\n<ul>\n  <li><strong>Koncepcja</strong>: wygląd surowego betonu z strukturą</li>\n  <li><strong>Efekt</strong>: industrialny, nowoczesny styl</li>\n  <li><strong>Technika</strong>: specjalna aplikacja spatułą</li>\n  <li><strong>Dopłata</strong>: +100-200 zł/m²</li>\n</ul>\n\n<h2>Cennik dla garaży domowych w Krakowie</h2>\n\n<h3>Przykładowe koszty z montażem:</h3>\n<ul>\n  <li><strong>Garaż 18 m²</strong> (1 stanowisko): 3240-5040 zł</li>\n  <li><strong>Garaż 24 m²</strong> (1,5 stanowiska): 4320-6480 zł</li>\n  <li><strong>Garaż 36 m²</strong> (2 stanowiska): 6480-10080 zł</li>\n  <li><strong>Garaż 48 m²</strong> (2,5 stanowiska): 8640-13440 zł</li>\n  <li><strong>Garaż 60 m²</strong> (3 stanowiska): 10800-16800 zł</li>\n</ul>\n\n<h3>Dodatki:</h3>\n<ul>\n  <li><strong>Cokoły żywiczne 10-15 cm</strong>: 35-50 zł/mb</li>\n  <li><strong>Drugi kolor/strefa</strong>: +30-50 zł/m²</li>\n  <li><strong>Floki dekoracyjne</strong>: +50-80 zł/m²</li>\n  <li><strong>Efekt metallic</strong>: +80-150 zł/m²</li>\n  <li><strong>Naprawa podłoża</strong>: 50-120 zł/m² (jeśli konieczna)</li>\n</ul>\n\n<h2>Proces realizacji</h2>\n<ol>\n  <li><strong>Kontakt i umówienie</strong> – telefon/email</li>\n  <li><strong>Wizyta w domu</strong> – bezpłatna wycena, pomiary, doradztwo</li>\n  <li><strong>Wybór systemu i koloru</strong> – katalogi, próbki</li>\n  <li><strong>Ustalenie terminu</strong> – dopasowanie do Twojego harmonogramu</li>\n  <li><strong>Realizacja</strong> – 2-4 dni w zależności od powierzchni</li>\n  <li><strong>Schnięcie</strong> – 24h chodzenie, 48-72h pojazd</li>\n  <li><strong>Odbiór</strong> – inspekcja, instrukcja pielęgnacji</li>\n  <li><strong>Gwarancja</strong> – 3-5 lat na wykonanie</li>\n</ol>\n\n<h2>Posadzka a ogrzewanie podłogowe</h2>\n<p>Wiele garaży w Krakowie ma ogrzewanie podłogowe. Posadzka żywiczna:</p>\n<ul>\n  <li><strong>Współpracuje z ogrzewaniem</strong> – dobra przewodność cieplna</li>\n  <li><strong>Warunki aplikacji</strong>: ogrzewanie wyłączone 3 dni przed i 7 dni po</li>\n  <li><strong>Eksploatacja</strong>: max temperatura podłoża 28°C (standardowo)</li>\n  <li><strong>Komfort</strong>: ciepła powierzchnia jesienią i zimą</li>\n  <li><strong>Uwaga</strong>: przy włączonym ogrzewaniu szybsze schnięcie żywicy</li>\n</ul>\n\n<h2>Porównanie rozwiązań dla garażu domowego</h2>\n<table>\n  <tr>\n    <th>Rozwiązanie</th>\n    <th>Cena garażu 30 m²</th>\n    <th>Trwałość</th>\n    <th>Estetyka</th>\n  </tr>\n  <tr>\n    <td>Beton nieimpregnowany</td>\n    <td>0 zł (istniejący)</td>\n    <td>10 lat</td>\n    <td>⭐</td>\n  </tr>\n  <tr>\n    <td>Farba epoksydowa</td>\n    <td>1800-2400 zł</td>\n    <td>3-5 lat</td>\n    <td>⭐⭐</td>\n  </tr>\n  <tr>\n    <td>Płytki przemysłowe</td>\n    <td>6000-9000 zł</td>\n    <td>25 lat</td>\n    <td>⭐⭐⭐⭐</td>\n  </tr>\n  <tr>\n    <td>Posadzka żywiczna</td>\n    <td>5400-8400 zł</td>\n    <td>25-30 lat</td>\n    <td>⭐⭐⭐⭐⭐</td>\n  </tr>\n</table>\n\n<h2>Specjalne wymagania</h2>\n\n<h3>Garaż-showroom (kolekcjonerzy aut)</h3>\n<ul>\n  <li><strong>System</strong>: poliuretan premium z topcoatem high-gloss</li>\n  <li><strong>Kolor</strong>: jednolity, często czarny lub grafitowy</li>\n  <li><strong>Efekt</strong>: lustrzane odbicia, efekt mokrej powierzchni</li>\n  <li><strong>Cena</strong>: 400-550 zł/m²</li>\n</ul>\n\n<h3>Garaż dla SUV/pojazdów ciężkich</h3>\n<ul>\n  <li><strong>System</strong>: epoksyd grubowarstwowy 4-5 mm</li>\n  <li><strong>Wzmocnienie</strong>: posypka kwarcowa gruba</li>\n  <li><strong>Uwaga</strong>: sprawdzenie nośności betonu</li>\n  <li><strong>Cena</strong>: 320-450 zł/m²</li>\n</ul>\n\n<h2>Pielęgnacja w garażu domowym</h2>\n<ul>\n  <li><strong>Codziennie</strong>: zamiatanie liści, piasku</li>\n  <li><strong>Tygodniowo</strong>: mycie mopem</li>\n  <li><strong>Miesięcznie</strong>: gruntowne mycie z detergentem</li>\n  <li><strong>Zimą</strong>: zmywanie soli natychmiast</li>\n  <li><strong>Co kilka lat</strong>: możliwość odświeżenia topcoatu (500-800 zł)</li>\n</ul>\n\n<h2>Dlaczego warto w Krakowie?</h2>\n<ul>\n  <li><strong>Rynek nieruchomości</strong> – wysoka wartość domów, inwestycja się zwraca</li>\n  <li><strong>Standard wykończenia</strong> – oczekiwania kupujących są wysokie</li>\n  <li><strong>Klimat</strong> – mroźne zimy i gorące lata wymagają odpornej posadzki</li>\n  <li><strong>Dostępność wykonawców</strong> – konkurencyjne ceny</li>\n  <li><strong>Łatwa konserwacja</strong> – oszczędność czasu dla zajętych właścicieli</li>\n</ul>\n\n<h2>Najczęstsze pytania właścicieli domów</h2>\n<p><strong>Czy można wykonać częściowo (tylko strefa postojowa)?</strong></p>\n<p>Tak, możemy zrobić np. 70% posadzki żywicznej, 30% zostawić jako strefa magazynowa. Oszczędność 20-30%.</p>\n\n<p><strong>Jak długo nie można korzystać z garażu?</strong></p>\n<p>Realnie 2-3 dni. Dzień prac + 2 dni schnięcia. Samochód można zaparkować na ulicy lub u sąsiada.</p>\n\n<p><strong>Czy mogę wybrać nietypowy kolor (np. niebieski)?</strong></p>\n<p>Tak, dostępne są setki kolorów RAL i NCS. Dopłata za kolor niestandardowy: 30-60 zł/m².</p>\n\n<p>Masz dom w Krakowie i chcesz profesjonalny garaż? <a href=\"/kontakt\">Skontaktuj się z nami</a> po bezpłatną wycenę i doradztwo. Obsługujemy wszystkie dzielnice Krakowa oraz okolice: Skawina, Mogilany, Niepołomice, Wieliczka. Realizacja od 2 dni!</p>\n\n<p>Zobacz też: <a href=\"/blog/posadzka-zywiczna-garaz-podziemny-krakow\">garaże podziemne</a> oraz <a href=\"/blog/posadzka-epoksydowa-garaz-wieliczka\">posadzki w Wieliczce</a>.</p>\n",
  "author": {
    "name": "Damian",
    "avatar": "/profilowe.png?height=40&width=40",
    "bio": "Specjalista ds. posadzek żywicznych"
  },
  "publishedAt": "2026-01-01",
  "updatedAt": "2026-01-01",
  "category": "Lokalne",
  "tags": [
    "posadzka żywiczna",
    "garaż domowy",
    "Kraków",
    "dom jednorodzinny",
    "posadzka epoksydowa",
    "garaż w domu"
  ],
  "readTime": "11 min",
  "image": {
    "url": "/garaz/jaka-posadzka-zywiczna-do-garazu.png?height=600&width=1200",
    "alt": "Posadzka żywiczna garaż domowy Kraków – idealna dla Twojego domu",
    "caption": "Posadzka żywiczna garaż domowy Kraków – idealna dla Twojego domu"
  },
  "seo": {
    "metaTitle": "Posadzka żywiczna garaż domowy Kraków | Dla domu jednorodzinnego",
    "metaDescription": "Posadzka żywiczna do garażu w domu jednorodzinnym w Krakowie. Systemy, ceny, kolory i realizacja dla właścicieli domów.",
    "keywords": [
      "posadzka żywiczna garaż domowy",
      "posadzka garaż Kraków",
      "dom jednorodzinny Kraków",
      "garaż w domu",
      "posadzka epoksydowa Kraków"
    ],
    "canonicalUrl": "https://posadzkizywiczne.com/blog/posadzka-zywiczna-garaz-domowy-krakow"
  },
  "featured": false,
  "status": "published"
}